vodo/__init__.py
vodo/api.py
vodo/config.py
vodo/main.py
vodo/models.py
vodo/ui.py
vodo-0.3.0.dist-info/licenses/LICENSE
vodo-0.3.0.dist-info/METADATA
vodo-0.3.0.dist-info/WHEEL
vodo-0.3.0.dist-info/entry_points.txt
vodo-0.3.0.dist-info/top_level.txt
vodo-0.3.0.dist-info/RECORD
