Metadata-Version: 2.4
Name: vodo
Version: 0.3.0
Summary: A Typer CLI to interact with a Vikunja instance
Author-email: Mark Pitblado <mark@pitbaldo.me>
License: Copyright 2025 Mark Pitblado <mark@pitblado.me>
Project-URL: Homepage, https://codeberg.org/mark-pitblado/vodo
Project-URL: Repository, https://codeberg.org/mark-pitblado/vodo
Project-URL: Issues, https://codeberg.org/mark-pitblado/vodo/issues
Requires-Python: >=3.11
License-File: LICENSE
Requires-Dist: typer>=0.15.2
Requires-Dist: httpx
Requires-Dist: pydantic
Requires-Dist: tomli
Requires-Dist: tomli-w
Requires-Dist: pytest
Dynamic: license-file
